testdata/clitable_templateA
testdata/clitable_templateB
testdata/clitable_templateC
testdata/clitable_templateD
testdata/default_index
testdata/nondefault_index
testdata/parseindex_index
testdata/parseindexfail1_index
testdata/parseindexfail2_index
testdata/parseindexfail3_index
textfsmplus/__init__.py
textfsmplus/clitable.py
textfsmplus/copyable_regex_object.py
textfsmplus/parser.py
textfsmplus/terminal.py
textfsmplus/texttable.py
textfsmplus-0.2.1.dist-info/COPYING
textfsmplus-0.2.1.dist-info/LICENSE.txt
textfsmplus-0.2.1.dist-info/METADATA
textfsmplus-0.2.1.dist-info/WHEEL
textfsmplus-0.2.1.dist-info/entry_points.txt
textfsmplus-0.2.1.dist-info/top_level.txt
textfsmplus-0.2.1.dist-info/RECORD
